{
    "AX": {
        "error": 0.051755821263653655, 
        "filter_outliers_dict": {
            "filter_outliers": true, 
            "iterations": 1, 
            "std_devs": 2
        }, 
        "fit": "average", 
        "value": -0.22508149437214198
    }, 
    "CDD": {
        "error": 4.522599341285429e-05, 
        "filter_outliers_dict": {
            "filter_outliers": true, 
            "iterations": 1, 
            "std_devs": 10
        }, 
        "fit": "average", 
        "value": 1.5012385847512633e-05
    }, 
    "H1": {
        "error": 0.03399398160777636, 
        "filter_outliers_dict": {
            "filter_outliers": true, 
            "iterations": 1, 
            "std_devs": 2
        }, 
        "fit": "average", 
        "value": -0.04836794468428707
    }, 
    "H2": {
        "error": 0.08941837408015008, 
        "filter_outliers_dict": {
            "filter_outliers": true, 
            "iterations": 1, 
            "std_devs": 2
        }, 
        "fit": "average", 
        "value": 0.06249822981270223
    }, 
    "L1": {
        "error": 0.019356859045962568, 
        "filter_outliers_dict": {
            "filter_outliers": true, 
            "iterations": 1, 
            "std_devs": 2
        }, 
        "fit": "average", 
        "value": -0.02709609973555479
    }, 
    "L2": {
        "error": 0.039998499308723116, 
        "filter_outliers_dict": {
            "filter_outliers": true, 
            "iterations": 1, 
            "std_devs": 2
        }, 
        "fit": "average", 
        "value": -0.02807129324069565
    }
}