{
    "AX": {
        "error": 0.0490415764022951, 
        "filter_outliers_dict": {
            "filter_outliers": true, 
            "iterations": 1, 
            "std_devs": 2
        }, 
        "fit": "average", 
        "value": -0.21921369637179577
    }, 
    "CDD": {
        "error": 3.0124478455902784e-05, 
        "filter_outliers_dict": {
            "filter_outliers": true, 
            "iterations": 1, 
            "std_devs": 10
        }, 
        "fit": "average", 
        "value": 6.25516076979693e-06
    }, 
    "H1": {
        "error": 0.03344494532591735, 
        "filter_outliers_dict": {
            "filter_outliers": true, 
            "iterations": 1, 
            "std_devs": 2
        }, 
        "fit": "average", 
        "value": -0.03954405448702777
    }, 
    "H2": {
        "error": 0.10427492300464446, 
        "filter_outliers_dict": {
            "filter_outliers": true, 
            "iterations": 1, 
            "std_devs": 2
        }, 
        "fit": "average", 
        "value": 0.028778816553421765
    }, 
    "L1": {
        "error": 0.01880181419683816, 
        "filter_outliers_dict": {
            "filter_outliers": true, 
            "iterations": 1, 
            "std_devs": 2
        }, 
        "fit": "average", 
        "value": -0.034595244570189844
    }, 
    "L2": {
        "error": 0.03712894501229759, 
        "filter_outliers_dict": {
            "filter_outliers": true, 
            "iterations": 1, 
            "std_devs": 2
        }, 
        "fit": "average", 
        "value": -0.027258874946871393
    }
}