{
    "Ar36": {
        "error": 0.00023581525696244932,
        "filter_outliers_dict": {
            "filter_outliers": true,
            "iterations": 1,
            "std_devs": 2
        },
        "fit": "Parabolic",
        "fn": 383,
        "include_baseline_error": false,
        "n": 400,
        "reviewed": true,
        "value": 0.012951051724409397
    },
    "Ar37": {
        "error": 0.008258328517523629,
        "filter_outliers_dict": {
            "filter_outliers": true,
            "iterations": 1,
            "std_devs": 2
        },
        "fit": "Parabolic",
        "fn": 381,
        "include_baseline_error": false,
        "n": 400,
        "reviewed": true,
        "value": 0.0496286781452621
    },
    "Ar38": {
        "error": 0.0019906137695079513,
        "filter_outliers_dict": {
            "filter_outliers": true,
            "iterations": 1,
            "std_devs": 2
        },
        "fit": "Linear",
        "fn": 379,
        "include_baseline_error": false,
        "n": 400,
        "reviewed": true,
        "value": 0.27619182811780063
    },
    "Ar39": {
        "error": 0.006719872554975806,
        "filter_outliers_dict": {
            "filter_outliers": true,
            "iterations": 1,
            "std_devs": 2
        },
        "fit": "Linear",
        "fn": 382,
        "include_baseline_error": false,
        "n": 400,
        "reviewed": true,
        "value": 23.821806269050754
    },
    "Ar40": {
        "error": 0.0865952662611176,
        "filter_outliers_dict": {
            "filter_outliers": true,
            "iterations": 1,
            "std_devs": 2
        },
        "fit": "Parabolic",
        "fn": 382,
        "include_baseline_error": false,
        "n": 400,
        "reviewed": true,
        "value": 2932.96641609021
    },
    "Ar41": {
        "error": 0.10983668967815076,
        "filter_outliers_dict": {
            "filter_outliers": true,
            "iterations": 1,
            "std_devs": 2
        },
        "fit": "linear",
        "value": -0.06475714823867797
    }
}