{
    "Ar36": {
        "error": 0.00023127720752889422,
        "filter_outliers_dict": {
            "filter_outliers": true,
            "iterations": 1,
            "std_devs": 2
        },
        "fit": "Parabolic",
        "fn": 380,
        "include_baseline_error": false,
        "n": 400,
        "reviewed": true,
        "value": 0.0129122110514031
    },
    "Ar37": {
        "error": 0.008468997697983108,
        "filter_outliers_dict": {
            "filter_outliers": true,
            "iterations": 1,
            "std_devs": 2
        },
        "fit": "Parabolic",
        "fn": 382,
        "include_baseline_error": false,
        "n": 400,
        "reviewed": true,
        "value": 0.02830976612773432
    },
    "Ar38": {
        "error": 0.0022631691574808025,
        "filter_outliers_dict": {
            "filter_outliers": true,
            "iterations": 1,
            "std_devs": 2
        },
        "fit": "Linear",
        "fn": 383,
        "include_baseline_error": false,
        "n": 400,
        "reviewed": true,
        "value": 0.09867817645279836
    },
    "Ar39": {
        "error": 0.006067390501615753,
        "filter_outliers_dict": {
            "filter_outliers": true,
            "iterations": 1,
            "std_devs": 2
        },
        "fit": "Linear",
        "fn": 380,
        "include_baseline_error": false,
        "n": 400,
        "reviewed": true,
        "value": 10.472730900914332
    },
    "Ar40": {
        "error": 0.04718976673742525,
        "filter_outliers_dict": {
            "filter_outliers": true,
            "iterations": 1,
            "std_devs": 2
        },
        "fit": "Parabolic",
        "fn": 381,
        "include_baseline_error": false,
        "n": 400,
        "reviewed": true,
        "value": 1302.2304481070714
    },
    "Ar41": {
        "error": 0.11365827237156628,
        "filter_outliers_dict": {
            "filter_outliers": true,
            "iterations": 1,
            "std_devs": 2
        },
        "fit": "linear",
        "value": 0.09727218304687513
    }
}