{
    "Ar36": {
        "error": 0.00020080606161423651,
        "filter_outliers_dict": {
            "filter_outliers": true,
            "iterations": 1,
            "std_devs": 2
        },
        "fit": "Parabolic",
        "fn": 376,
        "include_baseline_error": false,
        "n": 400,
        "reviewed": true,
        "value": 0.010074478695562352
    },
    "Ar37": {
        "error": 0.007792876910913934,
        "filter_outliers_dict": {
            "filter_outliers": true,
            "iterations": 1,
            "std_devs": 2
        },
        "fit": "Parabolic",
        "fn": 381,
        "include_baseline_error": false,
        "n": 400,
        "reviewed": true,
        "value": 0.046247794139189724
    },
    "Ar38": {
        "error": 0.0024375731532042685,
        "filter_outliers_dict": {
            "filter_outliers": true,
            "iterations": 1,
            "std_devs": 2
        },
        "fit": "Linear",
        "fn": 397,
        "include_baseline_error": false,
        "n": 400,
        "reviewed": true,
        "value": 0.14578448511461173
    },
    "Ar39": {
        "error": 0.006122170506949013,
        "filter_outliers_dict": {
            "filter_outliers": true,
            "iterations": 1,
            "std_devs": 2
        },
        "fit": "Linear",
        "fn": 381,
        "include_baseline_error": false,
        "n": 400,
        "reviewed": true,
        "value": 14.1191764964478
    },
    "Ar40": {
        "error": 0.06209379054170618,
        "filter_outliers_dict": {
            "filter_outliers": true,
            "iterations": 1,
            "std_devs": 2
        },
        "fit": "Parabolic",
        "fn": 382,
        "include_baseline_error": false,
        "n": 400,
        "reviewed": true,
        "value": 1741.772361944803
    },
    "Ar41": {
        "error": 0.10636613186143129,
        "filter_outliers_dict": {
            "filter_outliers": true,
            "iterations": 1,
            "std_devs": 2
        },
        "fit": "linear",
        "value": 0.10434044876543791
    }
}